msdev_django_moretools-1.1.0.dist-info/licenses/LICENSE
shortcmd/__init__.py
shortcmd/admin.py
shortcmd/apps.py
shortcmd/models.py
shortcmd/tests.py
shortcmd/views.py
shortcmd/management/__init__.py
shortcmd/management/commands/__init__.py
shortcmd/management/commands/cldb.py
shortcmd/management/commands/mksp.py
shortcmd/management/commands/mm.py
shortcmd/management/commands/rp.py
shortcmd/migrations/__init__.py
msdev_django_moretools-1.1.0.dist-info/METADATA
msdev_django_moretools-1.1.0.dist-info/WHEEL
msdev_django_moretools-1.1.0.dist-info/top_level.txt
msdev_django_moretools-1.1.0.dist-info/RECORD
