Metadata-Version: 2.4
Name: msdev-django_moretools
Version: 1.1.0
Summary: Python package containing shortcut functions for Django
Home-page: https://github.com/mariosuarezDEV/django_shortcuts
Author: Luis Mario Cervantes Suarez
Author-email: luismariosuarez@lumace.cloud
Classifier: Environment :: Web Environment
Classifier: Framework :: Django
Classifier: Intended Audience :: Developers
Classifier: License :: OSI Approved :: GNU General Public License v3 (GPLv3)
Classifier: Operating System :: OS Independent
Classifier: Programming Language :: Python
Classifier: Programming Language :: Python :: 3
Classifier: Programming Language :: Python :: 3.12
Classifier: Topic :: Internet :: WWW/HTTP
Requires-Python: >=3.12
License-File: LICENSE
Requires-Dist: Django>=5.1.7
Dynamic: author
Dynamic: author-email
Dynamic: classifier
Dynamic: description
Dynamic: description-content-type
Dynamic: home-page
Dynamic: license-file
Dynamic: requires-dist
Dynamic: requires-python
Dynamic: summary
